{
  "version": 3,
  "middleware": {
    "/": {
      "files": [
        "server/edge-runtime-webpack.js",
        "server/src/middleware.js"
      ],
      "name": "src/middleware",
      "page": "/",
      "matchers": [
        {
          "regexp": "^(?:\\/(_next\\/data\\/[^/]{1,}))?\\/dashboard(?:\\/((?:[^\\/#\\?]+?)(?:\\/(?:[^\\/#\\?]+?))*))?(\\.json)?[\\/#\\?]?$",
          "originalSource": "/dashboard/:path*"
        },
        {
          "regexp": "^(?:\\/(_next\\/data\\/[^/]{1,}))?\\/login(\\.json)?[\\/#\\?]?$",
          "originalSource": "/login"
        }
      ],
      "wasm": [],
      "assets": [],
      "env": {
        "__NEXT_BUILD_ID": "VoHoczSGfPI_HBLM5_mVI",
        "NEXT_SERVER_ACTIONS_ENCRYPTION_KEY": "95N+8/Xk3z4J3lNwQXR//HjBVsrbvyRN+DxK+5oz4cU=",
        "__NEXT_PREVIEW_MODE_ID": "e8b82bcdc4e220216e9cef0de000b85a",
        "__NEXT_PREVIEW_MODE_ENCRYPTION_KEY": "25dcbc5d86e4f25b12ad82911bef60bc720da05ffab79303f18acba4991efa23",
        "__NEXT_PREVIEW_MODE_SIGNING_KEY": "ded042ace4d9a15c8ce9853feb9634e703a3a040d0a7c2a6117bb600ba228978"
      }
    }
  },
  "functions": {},
  "sortedMiddleware": [
    "/"
  ]
}